potential_spork/__init__.py
potential_spork/renderers.py
potential_spork/util.py
potential_spork-0.1.0.dist-info/DESCRIPTION.rst
potential_spork-0.1.0.dist-info/METADATA
potential_spork-0.1.0.dist-info/RECORD
potential_spork-0.1.0.dist-info/WHEEL
potential_spork-0.1.0.dist-info/metadata.json
potential_spork-0.1.0.dist-info/top_level.txt
