Metadata-Version: 2.0
Name: potential-spork
Version: 0.1.0
Summary: Fixed Width Output for Django Rest Framework
Home-page: https://github.com/mharvey/potential_spork
Author: Morgan Harvey
Author-email: morganharvey@gmail.com
License: MIT license
Keywords: potential_spork
Platform: UNKNOWN
Classifier: Development Status :: 2 - Pre-Alpha
Classifier: Intended Audience :: Developers
Classifier: License :: OSI Approved :: MIT License
Classifier: Natural Language :: English
Classifier: Programming Language :: Python :: 3
Classifier: Programming Language :: Python :: 3.3
Classifier: Programming Language :: Python :: 3.4
Classifier: Programming Language :: Python :: 3.5
Classifier: Programming Language :: Python :: 3.6
Requires-Dist: FixedWidth (<2,>=1)
Requires-Dist: djangorestframework (<4,>=3.6)
